tidal_dl/__init__.py
tidal_dl/apiKey.py
tidal_dl/decryption.py
tidal_dl/download.py
tidal_dl/enums.py
tidal_dl/events.py
tidal_dl/gui.py
tidal_dl/model.py
tidal_dl/paths.py
tidal_dl/printf.py
tidal_dl/settings.py
tidal_dl/tidal.py
tidal_dl/lang/__init__.py
tidal_dl/lang/arabic.py
tidal_dl/lang/chinese.py
tidal_dl/lang/croatian.py
tidal_dl/lang/czech.py
tidal_dl/lang/danish.py
tidal_dl/lang/dutch.py
tidal_dl/lang/english.py
tidal_dl/lang/filipino.py
tidal_dl/lang/french.py
tidal_dl/lang/german.py
tidal_dl/lang/hungarian.py
tidal_dl/lang/italian.py
tidal_dl/lang/japanese.py
tidal_dl/lang/korean.py
tidal_dl/lang/language.py
tidal_dl/lang/norwegian.py
tidal_dl/lang/polish.py
tidal_dl/lang/portuguese.py
tidal_dl/lang/russian.py
tidal_dl/lang/spanish.py
tidal_dl/lang/turkish.py
tidal_dl/lang/ukrainian.py
tidal_dl/lang/vietnamese.py
tidal_dl-2022.10.31.1.dist-info/METADATA
tidal_dl-2022.10.31.1.dist-info/WHEEL
tidal_dl-2022.10.31.1.dist-info/entry_points.txt
tidal_dl-2022.10.31.1.dist-info/top_level.txt
tidal_dl-2022.10.31.1.dist-info/RECORD
