Metadata-Version: 2.1
Name: tidal-dl
Version: 2022.10.31.1
Summary: Tidal Music Downloader.
Home-page: UNKNOWN
Author: YaronH
Author-email: yaronhuang@foxmail.com
License: Apache2
Platform: any
Requires-Dist: aigpy (>=2022.7.8.1)
Requires-Dist: requests (>=2.22.0)
Requires-Dist: pycryptodome
Requires-Dist: pydub
Requires-Dist: prettytable
